MANIFEST.in
README.rst
setup.py
jsonpath_ng/__init__.py
jsonpath_ng/exceptions.py
jsonpath_ng/jsonpath.py
jsonpath_ng/lexer.py
jsonpath_ng/parser.py
jsonpath_ng/bin/__init__.py
jsonpath_ng/bin/jsonpath.py
jsonpath_ng/ext/__init__.py
jsonpath_ng/ext/arithmetic.py
jsonpath_ng/ext/filter.py
jsonpath_ng/ext/iterable.py
jsonpath_ng/ext/parser.py
jsonpath_ng/ext/string.py
jsonpath_ng_i.egg-info/PKG-INFO
jsonpath_ng_i.egg-info/SOURCES.txt
jsonpath_ng_i.egg-info/dependency_links.txt
jsonpath_ng_i.egg-info/entry_points.txt
jsonpath_ng_i.egg-info/requires.txt
jsonpath_ng_i.egg-info/top_level.txt
tests/__init__.py
tests/test_examples.py
tests/test_exceptions.py
tests/test_jsonpath.py
tests/test_jsonpath_rw_ext.py
tests/test_lexer.py
tests/test_parser.py
tests/bin/__init__.py
tests/bin/test1.json
tests/bin/test2.json
tests/bin/test_jsonpath.py